kyle/__init__.py
kyle/datasets.py
kyle/integrals.py
kyle/transformations.py
kyle/util.py
kyle/calibration/__init__.py
kyle/calibration/calibration_methods.py
kyle/calibration/model_calibrator.py
kyle/evaluation/__init__.py
kyle/evaluation/continuous.py
kyle/evaluation/discrete.py
kyle/evaluation/reliabilities.py
kyle/metrics/__init__.py
kyle/metrics/calibration_metrics.py
kyle/models/__init__.py
kyle/models/calibratable_model.py
kyle/models/resnet.py
kyle/sampling/__init__.py
kyle/sampling/fake_clf.py
kyle_calibration-0.1.7.dist-info/LICENSE.txt
kyle_calibration-0.1.7.dist-info/METADATA
kyle_calibration-0.1.7.dist-info/WHEEL
kyle_calibration-0.1.7.dist-info/top_level.txt
kyle_calibration-0.1.7.dist-info/RECORD
