Metadata-Version: 2.1
Name: kyle-calibration
Version: 0.1.7
Summary: appliedAI classifier calibration library
Home-page: https://github.com/appliedAI-Initiative/kyle
Author: appliedAI
License: MIT
Platform: UNKNOWN
Requires-Python: >=3.8
Requires-Dist: numpy (>=1.20.0)
Requires-Dist: scikit-learn (>=1.0)
Requires-Dist: matplotlib (>=3.2.1)
Requires-Dist: netcal (==1.2.0)
Requires-Dist: scipy (>=1.7.1)
Provides-Extra: docs
Requires-Dist: Sphinx (==3.2.1) ; extra == 'docs'
Requires-Dist: sphinxcontrib-websupport (==1.2.4) ; extra == 'docs'
Requires-Dist: sphinx-rtd-theme ; extra == 'docs'
Provides-Extra: test
Requires-Dist: pytest ; extra == 'test'
